MANIFEST.in
README.md
requirements.txt
setup.cfg
setup.py
colf/__init__.py
colf/colf.py
colf/colf_base.py
colf/colf_marshall.py
colf/colf_unmarshall.py
colf.egg-info/PKG-INFO
colf.egg-info/SOURCES.txt
colf.egg-info/dependency_links.txt
colf.egg-info/requires.txt
colf.egg-info/top_level.txt
colf.egg-info/zip-safe