Metadata-Version: 2.1
Name: colf
Version: 0.6.2
Summary: colf: Colfer serialization/deserialization for Python
Home-page: http://github.com/guilt/Colfer-Python
Author: Karthik Kumar Viswanathan
Author-email: karthikkumar@gmail.com
License: cc0-1.0
Keywords: colf colfer serialization deserialization
Platform: UNKNOWN
Classifier: Topic :: Software Development :: Libraries
Classifier: Programming Language :: Python :: 2.7
Classifier: Programming Language :: Python :: 3.6
Classifier: Programming Language :: Python :: 3.7
Classifier: Programming Language :: Python :: 3.8
